{
  "local": {
    "rpcUrl": "http://localhost:8000/soroban/rpc",
    "networkPassphrase": "Standalone Network ; February 2017",
    "contracts": {
      "vault": {
        "address": "CBCRM5IVMCIUCWHT6HA2LTOA54FXJHPWRBYDMZZVLTBVEFTQO7T2AI2F",
        "startLedger": 126
      },
      "positionManager": {
        "address": "CCAPQATOZJJECEJ4E3FCT5KCHSW2PE6XWYBYKESX3FWAHFX6YNXVI36D",
        "startLedger": 130
      },
      "configManager": {
        "address": "CBMKVHYTN6NTKRD47M34JN5G3DNV7D6KO5IXCVNC6UQDOX7N76NRQZ4U",
        "startLedger": 114
      },
      "oracleRouter": {
        "address": "CD5M4UGUZOYE4GNBDBW6VNBXBRLSWFDCGOXUSXM3RHC43PL7WWWHRNYX",
        "startLedger": 118
      },
      "oracle": {
        "address": "CARZCL5MJWYF3VC5DEIZ7PCSZSG3GJKZF52MKNWM7ZV7O6DO22LAMWBK",
        "startLedger": 120
      }
    }
  },
  "testnet": {
    "rpcUrl": "https://soroban-testnet.stellar.org",
    "networkPassphrase": "Test SDF Network ; September 2015",
    "contracts": {
      "vault": {
        "address": "",
        "startLedger": 0
      },
      "positionManager": {
        "address": "",
        "startLedger": 0
      },
      "configManager": {
        "address": "",
        "startLedger": 0
      },
      "oracleRouter": {
        "address": "",
        "startLedger": 0
      },
      "oracle": {
        "address": "",
        "startLedger": 0
      }
    }
  },
  "mainnet": {
    "rpcUrl": "https://soroban.stellar.org",
    "networkPassphrase": "Public Global Stellar Network ; September 2015",
    "contracts": {
      "vault": {
        "address": "",
        "startLedger": 0
      },
      "positionManager": {
        "address": "",
        "startLedger": 0
      },
      "configManager": {
        "address": "",
        "startLedger": 0
      },
      "oracleRouter": {
        "address": "",
        "startLedger": 0
      },
      "oracle": {
        "address": "",
        "startLedger": 0
      }
    }
  }
}
